setup.py
opengithub/__init__.py
opengithub/opengithub.py
opengithub.egg-info/PKG-INFO
opengithub.egg-info/SOURCES.txt
opengithub.egg-info/dependency_links.txt
opengithub.egg-info/entry_points.txt
opengithub.egg-info/top_level.txt
test/test_opengithub.py