Metadata-Version: 1.1
Name: opengithub
Version: 0.3.4
Summary: Open your project in GitHub from the command line.
Home-page: http://kevin.schaul.io
Author: Kevin Schaul
Author-email: kevin.schaul@gmail.com
License: MIT
Platform: UNKNOWN
Classifier: Development Status :: 4 - Beta
Classifier: Environment :: Console
Classifier: Intended Audience :: Developers
Classifier: License :: OSI Approved :: MIT License
Classifier: Natural Language :: English
Classifier: Operating System :: Unix
Classifier: Programming Language :: Python
Classifier: Topic :: Software Development
